spacemap/__init__.py
spacemap/_layouts.py
spacemap/_spacemap.py
spacemap/_utils.py
spacemap/umap_utils/__init__.py
spacemap/umap_utils/aligned_umap.py
spacemap/umap_utils/distances.py
spacemap/umap_utils/layouts.py
spacemap/umap_utils/parametric_umap.py
spacemap/umap_utils/plot.py
spacemap/umap_utils/sparse.py
spacemap/umap_utils/spectral.py
spacemap/umap_utils/umap_.py
spacemap/umap_utils/utils.py
spacemap/umap_utils/validation.py
spacemap_dr-0.1.0.dist-info/licenses/LICENSE
spacemap_dr-0.1.0.dist-info/METADATA
spacemap_dr-0.1.0.dist-info/WHEEL
spacemap_dr-0.1.0.dist-info/top_level.txt
spacemap_dr-0.1.0.dist-info/RECORD
