Metadata-Version: 2.4
Name: spacemap-dr
Version: 0.1.0
Summary: SpaceMAP: Visualizing High-dimensional data by Space Expansion
Author-email: Xinrui Zu <zuxinrui95@gmail.com>
License: MIT
Project-URL: Homepage, https://github.com/zuxinrui/SpaceMAP
Project-URL: Source, https://github.com/zuxinrui/SpaceMAP
Keywords: Dimensionality Reduction,t-SNE,UMAP,Representation Learning,ICML
Classifier: Intended Audience :: Science/Research
Classifier: Intended Audience :: Developers
Classifier: Programming Language :: Python
Classifier: Programming Language :: Python :: 3
Classifier: Programming Language :: Python :: 3 :: Only
Classifier: Programming Language :: Python :: 3.9
Classifier: Programming Language :: Python :: 3.10
Classifier: Programming Language :: Python :: 3.11
Classifier: Programming Language :: Python :: 3.12
Classifier: Programming Language :: Python :: Implementation :: CPython
Classifier: Programming Language :: C
Classifier: Topic :: Software Development
Classifier: Topic :: Scientific/Engineering
Classifier: Operating System :: Microsoft :: Windows
Classifier: Operating System :: POSIX
Classifier: Operating System :: Unix
Classifier: Operating System :: MacOS
Classifier: License :: OSI Approved :: MIT License
Requires-Python: >=3.9
License-File: LICENSE
Requires-Dist: scikit-learn>=0.24
Requires-Dist: numba>=0.55
Requires-Dist: faiss-cpu>=1.7.0
Requires-Dist: scipy>=1.7
Requires-Dist: ipywidgets>=7
Requires-Dist: matplotlib
Requires-Dist: torchvision
Requires-Dist: pynndescent
Dynamic: license-file
